{
  "indexes": [
    {
      "collectionGroup": "blogs",
      "queryScope": "COLLECTION",
      "fields": [
        {
          "fieldPath": "isPublished",
          "order": "ASCENDING"
        },
        {
          "fieldPath": "publishedAt",
          "order": "ASCENDING"
        },
        {
          "fieldPath": "__name__",
          "order": "ASCENDING"
        }
      ],
      "density": "SPARSE_ALL"
    },
    {
      "collectionGroup": "blogs",
      "queryScope": "COLLECTION",
      "fields": [
        {
          "fieldPath": "isPublished",
          "order": "ASCENDING"
        },
        {
          "fieldPath": "publishedAt",
          "order": "DESCENDING"
        },
        {
          "fieldPath": "__name__",
          "order": "DESCENDING"
        }
      ],
      "density": "SPARSE_ALL"
    },
    {
      "collectionGroup": "coupons",
      "queryScope": "COLLECTION",
      "fields": [
        {
          "fieldPath": "isActive",
          "order": "ASCENDING"
        },
        {
          "fieldPath": "expiryDate",
          "order": "ASCENDING"
        },
        {
          "fieldPath": "__name__",
          "order": "ASCENDING"
        }
      ],
      "density": "SPARSE_ALL"
    },
    {
      "collectionGroup": "orders",
      "queryScope": "COLLECTION",
      "fields": [
        {
          "fieldPath": "payment.paymentStatus",
          "order": "ASCENDING"
        },
        {
          "fieldPath": "createdAt",
          "order": "ASCENDING"
        },
        {
          "fieldPath": "__name__",
          "order": "ASCENDING"
        }
      ],
      "density": "SPARSE_ALL"
    },
    {
      "collectionGroup": "products",
      "queryScope": "COLLECTION",
      "fields": [
        {
          "fieldPath": "isActive",
          "order": "ASCENDING"
        },
        {
          "fieldPath": "stock",
          "order": "ASCENDING"
        },
        {
          "fieldPath": "__name__",
          "order": "ASCENDING"
        }
      ],
      "density": "SPARSE_ALL"
    },
    {
      "collectionGroup": "products",
      "queryScope": "COLLECTION",
      "fields": [
        {
          "fieldPath": "isActive",
          "order": "ASCENDING"
        },
        {
          "fieldPath": "stockQuantity",
          "order": "ASCENDING"
        },
        {
          "fieldPath": "__name__",
          "order": "ASCENDING"
        }
      ],
      "density": "SPARSE_ALL"
    }
  ],
  "fieldOverrides": []
}